pmd_django/__init__.py
pmd_django/api.py
pmd_django/apps.py
pmd_django/auth.py
pmd_django/query_helpers.py
pmd_django/testcases.py
pmd_django/views.py
pmd_django/generic_table/__init__.py
pmd_django/generic_table/generic_table.py
pmd_django/management/__init__.py
pmd_django/management/commands/__init__.py
pmd_django/management/commands/dev.py
pmd_django/management/commands/urls.py
pmd_django-2.0.14.dist-info/METADATA
pmd_django-2.0.14.dist-info/WHEEL
pmd_django-2.0.14.dist-info/licenses/LICENSE
pmd_django-2.0.14.dist-info/RECORD
