Metadata-Version: 2.4
Name: pmd-django
Version: 2.0.14
Author-email: TechServ Engineering Team <engineering@techserv.com>
License-Expression: MIT
License-File: LICENSE
Requires-Python: >=3.12
Requires-Dist: cerberus<1.4,>=1.3
Requires-Dist: django==5.*
Requires-Dist: jwcrypto<2.0,>=1.5
Requires-Dist: openpyxl<4.0,>=3.1
Provides-Extra: dev
Requires-Dist: coverage<8.0,>=7.6; extra == 'dev'
Requires-Dist: psycopg<4.0,>=3.2; extra == 'dev'
